<?xml version="1.0" encoding="utf-8" ?>
 <transforms>
   <Happy>
     <FacePosition>
       <x>7</x>
       <y>8</y>
       <z>9</z>
     </FacePosition>
     <FaceRotation>
       <x>1</x>
       <y>2</y>
       <z>3</z>
     </FaceRotation>
      <FacePosition>
       <x>7</x>
       <y>8</y>
       <z>9</z>
     </FacePosition>
     <FaceRotation>
       <x>1</x>
       <y>2</y>
       <z>3</z>
     </FaceRotation>
     <EyeRotation>
       <x>4</x>
       <y>5</y>
       <z>6</z>
     </EyeRotation>
   </Happy>
   <nervous>
     <FacePosition>
       <x>1</x>
       <y>2</y>
       <z>3</z>
     </FacePosition>
     <FaceRotation>
       <x>4</x>
       <y>5</y>
       <z>6</z>
     </FaceRotation>
     <EyeRotation>
       <x>7</x>
       <y>8</y>
       <z>9</z>
     </EyeRotation>
   </nervous>
   <inteligent>
     <FacePosition>
       <x>1</x>
       <y>2</y>
       <z>3</z>
     </FacePosition>
     <FaceRotation>
       <x>4</x>
       <y>5</y>
       <z>6</z>
     </FaceRotation>
     <EyeRotation>
       <x>7</x>
       <y>8</y>
       <z>9</z>
     </EyeRotation>
   </inteligent>
 </transforms>
